valuequant/ModelSets.py
valuequant/Models.py
valuequant/ResonanceModel.py
valuequant/StockFrameSets.py
valuequant/StockFrameSetsUS.py
valuequant/StockModelSets.py
valuequant/StockModels.py
valuequant/StockNet.py
valuequant/StockStrategyLocal.py
valuequant/VQconnect.py
valuequant/__init__.py
valuequant/commonform.py
valuequant/companyform.py
valuequant/companyformus.py
valuequant-1.1.5.dist-info/LICENSE.txt
valuequant-1.1.5.dist-info/METADATA
valuequant-1.1.5.dist-info/WHEEL
valuequant-1.1.5.dist-info/top_level.txt
valuequant-1.1.5.dist-info/RECORD
