Metadata-Version: 2.1
Name: valuequant
Version: 1.1.5
Summary: Provide stock value modeling and market factor analysis service.
Home-page: https://www.boomevolve.com/valuequant
Author: YE KAIWEN
Author-email: kevinye@originalbooms.com
License: MIT
Project-URL: Documentation, https://www.boomevolve.com/valuequant
Project-URL: Register, https://www.boomevolve.com/
Keywords: Quant,Data Science,Statistics,Value Analysis
Platform: UNKNOWN
Classifier: Development Status :: 5 - Production/Stable
Classifier: License :: OSI Approved :: MIT License
Classifier: Programming Language :: Python :: 3
Requires-Python: >=3
License-File: LICENSE.txt
Requires-Dist: pandas
Requires-Dist: requests
